{
  "config": {
    "organizerName": "Miguel Miramontes",
    "organizerPhone": "2093620911",
    "initialized": true
  },
  "participants": [
    {
      "slot": 1,
      "name": "Eddy"
    },
    {
      "slot": 2,
      "name": "Gloria"
    },
    {
      "slot": 3,
      "name": "Yaneth"
    },
    {
      "slot": 4,
      "name": "Andrea"
    },
    {
      "slot": 5,
      "name": "Sergio"
    },
    {
      "slot": 6,
      "name": "Carolina"
    },
    {
      "slot": 7,
      "name": "Sergito"
    },
    {
      "slot": 8,
      "name": "Miguel"
    },
    {
      "slot": 9,
      "name": "Stephanie"
    },
    {
      "slot": 10,
      "name": "Susy"
    },
    {
      "slot": 11,
      "name": "Inez"
    },
    {
      "slot": 12,
      "name": "Tommie"
    }
  ],
  "rounds": [
    {
      "round": 1,
      "collectDate": "2026-06-12",
      "payoutDate": "2026-06-13",
      "recipientSlot": 1,
      "payments": {
        "1": true,
        "2": true,
        "3": true,
        "4": true,
        "5": true,
        "6": true,
        "7": true,
        "8": true,
        "9": true,
        "10": true,
        "11": true,
        "12": true
      },
      "payoutSent": true,
      "notes": "Maria Gonzalez Ibarra - Carolina\nMaria Rojas - Andrea\n"
    },
    {
      "round": 2,
      "collectDate": "2026-06-26",
      "payoutDate": "2026-06-27",
      "recipientSlot": 2,
      "payments": {
        "1": false,
        "2": true,
        "3": false,
        "4": true,
        "5": false,
        "6": true,
        "7": false,
        "8": true,
        "9": true,
        "10": false,
        "11": false,
        "12": false
      },
      "payoutSent": false,
      "notes": ""
    },
    {
      "round": 3,
      "collectDate": "2026-07-10",
      "payoutDate": "2026-07-11",
      "recipientSlot": 3,
      "payments": {
        "1": false,
        "2": false,
        "3": false,
        "4": false,
        "5": false,
        "6": false,
        "7": false,
        "8": false,
        "9": false,
        "10": false,
        "11": false,
        "12": false
      },
      "payoutSent": false,
      "notes": ""
    },
    {
      "round": 4,
      "collectDate": "2026-07-24",
      "payoutDate": "2026-07-25",
      "recipientSlot": 4,
      "payments": {
        "1": false,
        "2": false,
        "3": false,
        "4": false,
        "5": false,
        "6": false,
        "7": false,
        "8": false,
        "9": false,
        "10": false,
        "11": false,
        "12": false
      },
      "payoutSent": false,
      "notes": ""
    },
    {
      "round": 5,
      "collectDate": "2026-08-07",
      "payoutDate": "2026-08-08",
      "recipientSlot": 5,
      "payments": {
        "1": false,
        "2": false,
        "3": false,
        "4": false,
        "5": false,
        "6": false,
        "7": false,
        "8": false,
        "9": false,
        "10": false,
        "11": false,
        "12": false
      },
      "payoutSent": false,
      "notes": ""
    },
    {
      "round": 6,
      "collectDate": "2026-08-21",
      "payoutDate": "2026-08-22",
      "recipientSlot": 6,
      "payments": {
        "1": false,
        "2": false,
        "3": false,
        "4": false,
        "5": false,
        "6": false,
        "7": false,
        "8": false,
        "9": false,
        "10": false,
        "11": false,
        "12": false
      },
      "payoutSent": false,
      "notes": ""
    },
    {
      "round": 7,
      "collectDate": "2026-09-04",
      "payoutDate": "2026-09-05",
      "recipientSlot": 7,
      "payments": {
        "1": false,
        "2": false,
        "3": false,
        "4": false,
        "5": false,
        "6": false,
        "7": false,
        "8": false,
        "9": false,
        "10": false,
        "11": false,
        "12": false
      },
      "payoutSent": false,
      "notes": ""
    },
    {
      "round": 8,
      "collectDate": "2026-09-18",
      "payoutDate": "2026-09-19",
      "recipientSlot": 8,
      "payments": {
        "1": false,
        "2": false,
        "3": false,
        "4": false,
        "5": false,
        "6": false,
        "7": false,
        "8": false,
        "9": false,
        "10": false,
        "11": false,
        "12": false
      },
      "payoutSent": false,
      "notes": ""
    },
    {
      "round": 9,
      "collectDate": "2026-10-02",
      "payoutDate": "2026-10-03",
      "recipientSlot": 9,
      "payments": {
        "1": false,
        "2": false,
        "3": false,
        "4": false,
        "5": false,
        "6": false,
        "7": false,
        "8": false,
        "9": false,
        "10": false,
        "11": false,
        "12": false
      },
      "payoutSent": false,
      "notes": ""
    },
    {
      "round": 10,
      "collectDate": "2026-10-16",
      "payoutDate": "2026-10-17",
      "recipientSlot": 10,
      "payments": {
        "1": false,
        "2": false,
        "3": false,
        "4": false,
        "5": false,
        "6": false,
        "7": false,
        "8": false,
        "9": false,
        "10": false,
        "11": false,
        "12": false
      },
      "payoutSent": false,
      "notes": ""
    },
    {
      "round": 11,
      "collectDate": "2026-10-30",
      "payoutDate": "2026-10-31",
      "recipientSlot": 11,
      "payments": {
        "1": false,
        "2": false,
        "3": false,
        "4": false,
        "5": false,
        "6": false,
        "7": false,
        "8": false,
        "9": false,
        "10": false,
        "11": false,
        "12": false
      },
      "payoutSent": false,
      "notes": ""
    },
    {
      "round": 12,
      "collectDate": "2026-11-13",
      "payoutDate": "2026-11-14",
      "recipientSlot": 12,
      "payments": {
        "1": false,
        "2": false,
        "3": false,
        "4": false,
        "5": false,
        "6": false,
        "7": false,
        "8": false,
        "9": false,
        "10": false,
        "11": false,
        "12": false
      },
      "payoutSent": false,
      "notes": ""
    }
  ]
}